frame_transforms/__init__.py
frame_transforms/transforms.py
frame_transforms/utils.py
frame_transforms-0.3.1.dist-info/METADATA
frame_transforms-0.3.1.dist-info/WHEEL
frame_transforms-0.3.1.dist-info/RECORD
