Metadata-Version: 2.4
Name: frame-transforms
Version: 0.3.1
Summary: Automatically compute and apply coordinate frame transformations
Project-URL: Homepage, https://github.com/MinhxNguyen7/FrameTransforms/
Keywords: coordinate,frame,geometry,pose,robotics,transformation
Classifier: License :: OSI Approved :: Apache Software License
Classifier: Programming Language :: Python
Classifier: Programming Language :: Python :: 3
Classifier: Programming Language :: Python :: 3.10
Classifier: Programming Language :: Python :: 3.11
Classifier: Programming Language :: Python :: 3.12
Classifier: Programming Language :: Python :: 3.13
Requires-Python: >=3.10
Requires-Dist: numpy>=2.2
Requires-Dist: scipy>=1.15
Provides-Extra: build
Requires-Dist: build>=1.2.2; extra == 'build'
Requires-Dist: hatchling; extra == 'build'
Requires-Dist: twine>=6.1.0; extra == 'build'
Provides-Extra: dev
Requires-Dist: flake8>=7.3; extra == 'dev'
Requires-Dist: isort>=5.12; extra == 'dev'
Requires-Dist: scipy-stubs>=1.15; extra == 'dev'
Provides-Extra: test
Requires-Dist: pytest-cov>=4.0; extra == 'test'
Requires-Dist: pytest>=8.4; extra == 'test'
